serde/__init__.py
serde/exceptions.py
serde/fields.py
serde/model.py
serde/tags.py
serde/utils.py
serde/validators.py
serde-0.9.0.dist-info/LICENSE-APACHE
serde-0.9.0.dist-info/LICENSE-MIT
serde-0.9.0.dist-info/METADATA
serde-0.9.0.dist-info/WHEEL
serde-0.9.0.dist-info/top_level.txt
serde-0.9.0.dist-info/RECORD
