Metadata-Version: 2.1
Name: serde
Version: 0.9.0
Summary: Define, serialize, deserialize, and validate Python data structures.
Home-page: https://github.com/rossmacarthur/serde
Download-URL: https://github.com/rossmacarthur/serde/archive/0.9.0.tar.gz
Author: Ross MacArthur
Author-email: ross@macarthur.io
License: MIT/Apache-2.0
Project-URL: Documentation, https://rossmacarthur.github.io/serde/
Project-URL: Issue Tracker, https://github.com/rossmacarthur/serde/issues
Keywords: serde serialization deserialization validation schema json
Classifier: License :: OSI Approved :: Apache Software License
Classifier: License :: OSI Approved :: MIT License
Classifier: Natural Language :: English
Classifier: Operating System :: OS Independent
Classifier: Programming Language :: Python
Classifier: Programming Language :: Python :: 3.7
Classifier: Programming Language :: Python :: 3.8
Classifier: Programming Language :: Python :: 3.9
Classifier: Programming Language :: Python :: 3.10
Classifier: Programming Language :: Python :: Implementation :: CPython
Requires-Python: >=3.7
License-File: LICENSE-APACHE
License-File: LICENSE-MIT
Provides-Extra: ext
Requires-Dist: chardet (==3.*) ; extra == 'ext'
Requires-Dist: validators (>=0.12.0) ; extra == 'ext'
